ImageSeeker/__init__.py
ImageSeeker/main.py
ImageSeeker/predict.py
ImageSeeker/train_engine.py
ImageSeeker/com_in_ineuron_ai_utils/__init__.py
ImageSeeker/com_in_ineuron_ai_utils/utils.py
ImageSeeker/static/assets/favicon.ico
ImageSeeker/static/assets/img/ImageSeeker.png
ImageSeeker/static/assets/img/bg-masthead.jpg
ImageSeeker/static/assets/img/form-v9.jpg
ImageSeeker/static/assets/img/portfolio/fullsize/1.jpg
ImageSeeker/static/assets/img/portfolio/fullsize/2.jpg
ImageSeeker/static/assets/img/portfolio/fullsize/3.jpg
ImageSeeker/static/assets/img/portfolio/fullsize/4.jpg
ImageSeeker/static/assets/img/portfolio/fullsize/5.jpg
ImageSeeker/static/assets/img/portfolio/fullsize/6.jpg
ImageSeeker/static/assets/img/portfolio/thumbnails/1.jpg
ImageSeeker/static/assets/img/portfolio/thumbnails/2.jpg
ImageSeeker/static/assets/img/portfolio/thumbnails/3.jpg
ImageSeeker/static/assets/img/portfolio/thumbnails/4.jpg
ImageSeeker/static/assets/img/portfolio/thumbnails/5.jpg
ImageSeeker/static/assets/img/portfolio/thumbnails/6.jpg
ImageSeeker/static/css/styles.css
ImageSeeker/static/css2/nunito-font.css
ImageSeeker/static/css2/style.css
ImageSeeker/static/js/scripts.js
ImageSeeker/templates/index.html
ImageSeeker/templates/input_form.html
ImageSeeker/templates/predict.html
ImageSeeker/utils/__init__.py
ImageSeeker/utils/callbacks.py
ImageSeeker/utils/config.py
ImageSeeker/utils/data_manager.py
ImageSeeker/utils/model.py
ImageSeeker/utils/models_config.py
ImageSeeker-0.7.dist-info/LICENSE
ImageSeeker-0.7.dist-info/LICENSE.txt
ImageSeeker-0.7.dist-info/METADATA
ImageSeeker-0.7.dist-info/WHEEL
ImageSeeker-0.7.dist-info/entry_points.txt
ImageSeeker-0.7.dist-info/top_level.txt
ImageSeeker-0.7.dist-info/RECORD
