Metadata-Version: 2.1
Name: ImageSeeker
Version: 0.7
Summary: Its an auto image classification library
Home-page: https://github.com/entbappy/ImageSeeker-Package
Author: Bappy Ahmed
Author-email: entbappy73@gmail.com
License: MIT
Keywords: imageseeker
Platform: UNKNOWN
Classifier: Development Status :: 3 - Alpha
Classifier: Intended Audience :: Developers
Classifier: Topic :: Software Development :: Build Tools
Classifier: License :: OSI Approved :: MIT License
Classifier: Programming Language :: Python :: 3
Classifier: Programming Language :: Python :: 3.4
Classifier: Programming Language :: Python :: 3.5
Classifier: Programming Language :: Python :: 3.6
License-File: LICENSE
License-File: LICENSE.txt
Requires-Dist: tensorflow (==2.4.1)
Requires-Dist: scipy (==1.6.3)
Requires-Dist: numpy
Requires-Dist: pandas
Requires-Dist: Pillow (==8.3.2)
Requires-Dist: Flask
Requires-Dist: Flask-Cors (==3.0.10)
